title_grabber/__init__.py
title_grabber/__main__.py
title_grabber_cristianrasch-0.2.0.dist-info/LICENSE
title_grabber_cristianrasch-0.2.0.dist-info/METADATA
title_grabber_cristianrasch-0.2.0.dist-info/WHEEL
title_grabber_cristianrasch-0.2.0.dist-info/top_level.txt
title_grabber_cristianrasch-0.2.0.dist-info/RECORD
