Metadata-Version: 2.1
Name: title-grabber-cristianrasch
Version: 0.2.0
Summary: Grabs page & article titles from lists of URLs contained in files passed in as arguments
Home-page: https://github.com/cristianrasch/title_grabber
Author: Cristian Rasch
Author-email: cristianrasch@fastmail.fm
License: UNKNOWN
Platform: UNKNOWN
Classifier: Programming Language :: Python :: 3
Classifier: License :: OSI Approved :: MIT License
Classifier: Operating System :: OS Independent
Requires-Dist: requests
Requires-Dist: beautifulsoup4
